agaro/__init__.py
agaro/measure_utils.py
agaro/output_utils.py
agaro/run_utils.py
agaro/runner.py
agaro-0.2.0.dist-info/DESCRIPTION.rst
agaro-0.2.0.dist-info/METADATA
agaro-0.2.0.dist-info/metadata.json
agaro-0.2.0.dist-info/pbr.json
agaro-0.2.0.dist-info/RECORD
agaro-0.2.0.dist-info/top_level.txt
agaro-0.2.0.dist-info/WHEEL
