Metadata-Version: 2.0
Name: agaro
Version: 0.2.0
Summary: Framework to run models
Home-page: https://github.com/eddiejessup/agaro
Author: Elliot Marsden
Author-email: elliot.marsden@gmail.com
License: BSD
Keywords: agaro
Platform: UNKNOWN
Classifier: Development Status :: 4 - Beta
Classifier: Intended Audience :: Science/Research
Classifier: Topic :: Scientific/Engineering
Classifier: License :: OSI Approved :: BSD License
Classifier: Natural Language :: English
Classifier: Programming Language :: Python :: 2
Classifier: Programming Language :: Python :: 2.6
Classifier: Programming Language :: Python :: 2.7
Classifier: Programming Language :: Python :: 3
Classifier: Programming Language :: Python :: 3.3
Classifier: Programming Language :: Python :: 3.4
Requires-Dist: numpy
Requires-Dist: scipy
Requires-Dist: ciabatta
